django_simple_stats-0.7.6.dist-info/licenses/LICENSE
simple_stats/__init__.py
simple_stats/stats.py
django_simple_stats-0.7.6.dist-info/METADATA
django_simple_stats-0.7.6.dist-info/WHEEL
django_simple_stats-0.7.6.dist-info/top_level.txt
django_simple_stats-0.7.6.dist-info/RECORD
