Metadata-Version: 2.4
Name: django-simple-stats
Version: 0.7.6
Summary: A django package for creating simple stats from a query
Home-page: https://github.com/spapas/django-simple-stats
Author: Serafeim Papastefanos
Author-email: Serafeim Papastefanos <spapas@gmail.com>
License: MIT
Classifier: Environment :: Web Environment
Classifier: Programming Language :: Python
Classifier: Programming Language :: Python :: 3
Classifier: Programming Language :: Python :: 3.11
Classifier: Programming Language :: Python :: 3.12
Classifier: Framework :: Django
Classifier: Framework :: Django :: 4.2
Classifier: Framework :: Django :: 5.2
Classifier: Intended Audience :: Developers
Classifier: Operating System :: OS Independent
Classifier: Topic :: Internet :: WWW/HTTP
Classifier: Topic :: Software Development :: Libraries
Requires-Python: >=3.7
License-File: LICENSE
Requires-Dist: Django>=3.0
Requires-Dist: six
Dynamic: author
Dynamic: home-page
Dynamic: license-file
